tableY/combining.py
tableY-0.1.3.dist-info/METADATA
tableY-0.1.3.dist-info/WHEEL
tableY-0.1.3.dist-info/top_level.txt
tableY-0.1.3.dist-info/RECORD
