Metadata-Version: 2.1
Name: tableY
Version: 0.1.3
Summary: Convert the columns of the table to json
Home-page: https://github.com/tyj-1995
Author: White.tie
Author-email: 1042798703@qq.com
License: UNKNOWN
Platform: UNKNOWN
Classifier: Environment :: Web Environment
Classifier: Intended Audience :: Developers
Classifier: Operating System :: OS Independent
Classifier: Topic :: Text Processing :: Indexing
Classifier: Topic :: Utilities
Classifier: Topic :: Internet
Classifier: Topic :: Software Development :: Libraries :: Python Modules
Classifier: Programming Language :: Python
Classifier: Programming Language :: Python :: 2.6
Classifier: Programming Language :: Python :: 3.6
Requires-Dist: pandas
